nonebot_plugin_wordle/__init__.py
nonebot_plugin_wordle/data_source.py
nonebot_plugin_wordle/resources/fonts/KarnakPro-Bold.ttf
nonebot_plugin_wordle/resources/words/CET4.json
nonebot_plugin_wordle/resources/words/CET6.json
nonebot_plugin_wordle/resources/words/GMAT.json
nonebot_plugin_wordle/resources/words/GRE.json
nonebot_plugin_wordle/resources/words/IELTS.json
nonebot_plugin_wordle/resources/words/SAT.json
nonebot_plugin_wordle/resources/words/TOEFL.json
nonebot_plugin_wordle/resources/words/专八.json
nonebot_plugin_wordle/resources/words/专四.json
nonebot_plugin_wordle/resources/words/考研.json
nonebot_plugin_wordle/utils.py
nonebot_plugin_wordle-0.4.5.dist-info/LICENSE
nonebot_plugin_wordle-0.4.5.dist-info/METADATA
nonebot_plugin_wordle-0.4.5.dist-info/WHEEL
nonebot_plugin_wordle-0.4.5.dist-info/RECORD
