Metadata-Version: 2.1
Name: nonebot_plugin_wordle
Version: 0.4.5
Summary: Nonebot2 wordle猜单词插件
Home-page: https://github.com/noneplugin/nonebot-plugin-wordle
License: MIT
Author: meetwq
Author-email: meetwq@gmail.com
Requires-Python: >=3.9,<4.0
Classifier: License :: OSI Approved :: MIT License
Classifier: Programming Language :: Python :: 3
Classifier: Programming Language :: Python :: 3.9
Classifier: Programming Language :: Python :: 3.10
Classifier: Programming Language :: Python :: 3.11
Classifier: Programming Language :: Python :: 3.12
Classifier: Programming Language :: Python :: 3.13
Requires-Dist: nonebot-plugin-alconna (>=0.45.1,<1.0.0)
Requires-Dist: nonebot-plugin-uninfo (>=0.4.0,<1.0.0)
Requires-Dist: nonebot2 (>=2.3.0,<3.0.0)
Requires-Dist: pillow (>=10.0.0,<11.0.0)
Requires-Dist: pyspellchecker (>=0.8.0,<0.9.0)
Project-URL: Repository, https://github.com/noneplugin/nonebot-plugin-wordle
